dcsv/__init__.py
dcsv/client.py
dcsv/gateway.py
dcsv/http.py
dcsv/intents.py
dcsv/ratelimit.py
dcsv/utils.py
dcsv_py-1.0.3.dist-info/METADATA
dcsv_py-1.0.3.dist-info/WHEEL
dcsv_py-1.0.3.dist-info/top_level.txt
dcsv_py-1.0.3.dist-info/RECORD
