Metadata-Version: 2.4
Name: dcsv-py
Version: 1.0.3
Summary: Ultra High Performance, Stackless Discord Library for Python
Home-page: https://github.com/DiscordSunucu/dcsv-py
Author: DCSV Team
Author-email: DCSV Team <you@example.com>
License: MIT
Project-URL: Homepage, https://github.com/DiscordSunucu/dcsv-py
Project-URL: Repository, https://github.com/DiscordSunucu/dcsv-py.git
Project-URL: Issues, https://github.com/DiscordSunucu/dcsv-py/issues
Keywords: discord,bot,api,async,websocket,discord-library
Classifier: Development Status :: 4 - Beta
Classifier: Intended Audience :: Developers
Classifier: License :: OSI Approved :: MIT License
Classifier: Programming Language :: Python :: 3
Classifier: Programming Language :: Python :: 3.8
Classifier: Programming Language :: Python :: 3.9
Classifier: Programming Language :: Python :: 3.10
Classifier: Programming Language :: Python :: 3.11
Classifier: Programming Language :: Python :: 3.12
Classifier: Topic :: Software Development :: Libraries :: Python Modules
Classifier: Topic :: Communications :: Chat
Requires-Python: >=3.8
Requires-Dist: aiohttp>=3.8.0
Requires-Dist: websockets>=11.0
Dynamic: author
Dynamic: home-page
Dynamic: requires-python
